codegen.py
pytest_ast_back_to_python.py
pytest_ast_back_to_python-1.2.1.dist-info/LICENSE
pytest_ast_back_to_python-1.2.1.dist-info/METADATA
pytest_ast_back_to_python-1.2.1.dist-info/WHEEL
pytest_ast_back_to_python-1.2.1.dist-info/entry_points.txt
pytest_ast_back_to_python-1.2.1.dist-info/top_level.txt
pytest_ast_back_to_python-1.2.1.dist-info/RECORD
