Metadata-Version: 2.1
Name: pytest-ast-back-to-python
Version: 1.2.1
Summary: A plugin for pytest devs to view how assertion rewriting recodes the AST
Home-page: https://github.com/tomviner/pytest-ast-back-to-python
Author: Tom Viner
Author-email: code@viner.tv
Maintainer: Tom Viner
Maintainer-email: code@viner.tv
License: BSD-3
Platform: UNKNOWN
Classifier: Development Status :: 4 - Beta
Classifier: Intended Audience :: Developers
Classifier: Topic :: Software Development :: Testing
Classifier: Programming Language :: Python
Classifier: Programming Language :: Python :: 2
Classifier: Programming Language :: Python :: 2.7
Classifier: Programming Language :: Python :: 3
Classifier: Programming Language :: Python :: 3.3
Classifier: Programming Language :: Python :: 3.4
Classifier: Programming Language :: Python :: 3.5
Classifier: Programming Language :: Python :: Implementation :: CPython
Classifier: Programming Language :: Python :: Implementation :: PyPy
Classifier: Operating System :: OS Independent
Classifier: License :: OSI Approved :: BSD License
Requires-Dist: pytest
